llm_traceguard/__init__.py
llm_traceguard/instrument.py
llm_traceguard-0.0.1.dev0.dist-info/LICENSE
llm_traceguard-0.0.1.dev0.dist-info/METADATA
llm_traceguard-0.0.1.dev0.dist-info/WHEEL
llm_traceguard-0.0.1.dev0.dist-info/RECORD
