Metadata-Version: 2.1
Name: llm-traceguard
Version: 0.0.1.dev0
Summary: End-to-end observability with built-in security guardrails.
License: Apache-2.0
Author: WhyLabs.ai
Author-email: support@whylabs.ai
Requires-Python: >=3.8,<4.0
Classifier: License :: OSI Approved :: Apache Software License
Classifier: Programming Language :: Python :: 3
Classifier: Programming Language :: Python :: 3.8
Classifier: Programming Language :: Python :: 3.9
Classifier: Programming Language :: Python :: 3.10
Classifier: Programming Language :: Python :: 3.11
Requires-Dist: opentelemetry-api (>=1.21.0,<2.0.0)
Requires-Dist: opentelemetry-sdk (>=1.21.0,<2.0.0)
